rock_scissors_paper_framework/__init__.py
rock_scissors_paper_framework/rsp.py
rock_scissors_paper_framework-1.0.0.dist-info/LICENSE
rock_scissors_paper_framework-1.0.0.dist-info/METADATA
rock_scissors_paper_framework-1.0.0.dist-info/WHEEL
rock_scissors_paper_framework-1.0.0.dist-info/entry_points.txt
rock_scissors_paper_framework-1.0.0.dist-info/RECORD
