Metadata-Version: 2.1
Name: rock_scissors_paper_framework
Version: 1.0.0
Summary: A modular framework for Rock-Paper-Scissors game.
Home-page: https://github.com/JamzTyson/Rock_Scissors_Paper
License: MIT
Keywords: rock,scissors,paper,python,game
Author: JamzTyson
Author-email: 151654652+JamzTyson@users.noreply.github.com
Requires-Python: >=3.10.11,<4.0.0
Classifier: License :: OSI Approved :: MIT License
Classifier: Programming Language :: Python :: 3
Classifier: Programming Language :: Python :: 3.11
Classifier: Programming Language :: Python :: 3.12
Classifier: Programming Language :: Python :: 3.13
Project-URL: Repository, https://github.com/JamzTyson/Rock_Scissors_Paper
